odoo/addons/queued_sale_notify/README.rst
odoo/addons/queued_sale_notify/__init__.py
odoo/addons/queued_sale_notify/__manifest__.py
odoo/addons/queued_sale_notify/i18n/es.po
odoo/addons/queued_sale_notify/models/__init__.py
odoo/addons/queued_sale_notify/models/sale_activity_notify.py
odoo/addons/queued_sale_notify/models/sale_mail_notify.py
odoo/addons/queued_sale_notify/models/sale_note_notify.py
odoo/addons/queued_sale_notify/models/sale_notify_mixin.py
odoo/addons/queued_sale_notify/models/sale_order.py
odoo/addons/queued_sale_notify/models/sale_order_type.py
odoo/addons/queued_sale_notify/readme/CONFIGURE.md
odoo/addons/queued_sale_notify/readme/CONTRIBUTORS.md
odoo/addons/queued_sale_notify/readme/DESCRIPTION.md
odoo/addons/queued_sale_notify/readme/ROADMAP.md
odoo/addons/queued_sale_notify/security/ir.model.access.csv
odoo/addons/queued_sale_notify/security/queued_sale_notify_security.xml
odoo/addons/queued_sale_notify/static/description/icon.png
odoo/addons/queued_sale_notify/static/description/index.html
odoo/addons/queued_sale_notify/tests/__init__.py
odoo/addons/queued_sale_notify/tests/test_queued_sale_notify.py
odoo/addons/queued_sale_notify/views/sale_order.xml
odoo/addons/queued_sale_notify/views/sale_order_type_view.xml
odoo_addon_queued_sale_notify-17.0.1.1.0.dist-info/METADATA
odoo_addon_queued_sale_notify-17.0.1.1.0.dist-info/WHEEL
odoo_addon_queued_sale_notify-17.0.1.1.0.dist-info/top_level.txt
odoo_addon_queued_sale_notify-17.0.1.1.0.dist-info/RECORD
